django_urls_templatetag/__init__.py
django_urls_templatetag/utils.py
django_urls_templatetag/templates/django_urls_templatetag/urls_js.html
django_urls_templatetag/templatetags/__init__.py
django_urls_templatetag/templatetags/django_urls.py
django_urls_templatetag-0.9.1.dist-info/METADATA
django_urls_templatetag-0.9.1.dist-info/WHEEL
django_urls_templatetag-0.9.1.dist-info/licenses/LICENSE
django_urls_templatetag-0.9.1.dist-info/RECORD
